pynmcli
