Metadata-Version: 1.0
Name: pynmcli
Version: 1.0.3
Summary: Simple python interface to Network Manager CLI
Home-page: https://github.com/fbarresi/PyNmcli
Author: Federico Barresi
Author-email: fede.barresi@gmail.com
License: MIT
Platform: UNKNOWN
